{
  "Version": "2012-10-17",
  "Statement": [
    {
      "Sid": "AllowPutOnlyOnBucket",
      "Effect": "Allow",
      "Action": [
        "s3:PutObject",
        "s3:PutObjectAcl"
      ],
      "Resource": "${bucket_arn}/*"
    },
    {
      "Sid": "AllowBucketListForPrefixMatch",
      "Effect": "Allow",
      "Action": [
        "s3:ListBucket"
      ],
      "Resource": "${bucket_arn}",
      "Condition": {
        "StringLike": {
          "s3:prefix": "logs/*"
        }
      }
    },
    {
      "Sid": "AllowCloudWatchLogs",
      "Effect": "Allow",
      "Action": [
        "logs:CreateLogGroup",
        "logs:CreateLogStream",
        "logs:PutLogEvents",
        "logs:DescribeLogStreams"
      ],
      "Resource": "*"
    },
    {
      "Sid": "AllowSSMAgent",
      "Effect": "Allow",
      "Action": [
        "ssm:DescribeAssociation",
        "ssm:GetDeployablePatchSnapshotForInstance",
        "ssm:GetDocument",
        "ssm:DescribeDocument",
        "ssm:GetManifest",
        "ssm:GetParameter",
        "ssm:GetParameters",
        "ssm:ListAssociations",
        "ssm:ListInstanceAssociations",
        "ssm:PutInventory",
        "ssm:PutComplianceItems",
        "ssm:PutConfigurePackageResult",
        "ssm:UpdateAssociationStatus",
        "ssm:UpdateInstanceAssociationStatus",
        "ssm:UpdateInstanceInformation",
        "ssmmessages:CreateControlChannel",
        "ssmmessages:CreateDataChannel",
        "ssmmessages:OpenControlChannel",
        "ssmmessages:OpenDataChannel",
        "ec2messages:AcknowledgeMessage",
        "ec2messages:DeleteMessage",
        "ec2messages:FailMessage",
        "ec2messages:GetEndpoint",
        "ec2messages:GetMessages",
        "ec2messages:SendReply"
      ],
      "Resource": "*"
    }
  ]
}
